abtest/__init__.py
abtest/ab_client.py
abtest/abtest_builder.py
abtest/const.py
abtest/proto.py
abtest_sdk-1.0.0.dist-info/METADATA
abtest_sdk-1.0.0.dist-info/WHEEL
abtest_sdk-1.0.0.dist-info/top_level.txt
abtest_sdk-1.0.0.dist-info/RECORD
