Metadata-Version: 2.1
Name: abtest-sdk
Version: 1.0.0
Summary: ab SDK for phoenix
Home-page: https://github.com/phoenix-rec/abtest-sdk-python
Author: 
Author-email: 
Requires-Dist: requests
Requires-Dist: setuptools
